setup.py
getmole/Get_molecule_h5_file_v5.0.py
getmole/__init__.py
getmole.egg-info/PKG-INFO
getmole.egg-info/SOURCES.txt
getmole.egg-info/dependency_links.txt
getmole.egg-info/not-zip-safe
getmole.egg-info/top_level.txt