Metadata-Version: 1.0
Name: getmole
Version: 0.1
Summary: get molecule file
Home-page: http://github.com/maiziex/getmole
Author: maiziex
Author-email: maiziex@gmail.com
License: MIT
Platform: UNKNOWN
